just_agents/base_agent.py
just_agents/base_memory.py
just_agents/data_classes.py
just_agents/interfaces/__init__.py
just_agents/interfaces/agent.py
just_agents/interfaces/function_call.py
just_agents/interfaces/memory.py
just_agents/interfaces/protocol_adapter.py
just_agents/just_async.py
just_agents/just_bus.py
just_agents/just_locator.py
just_agents/just_profile.py
just_agents/just_schema.py
just_agents/just_serialization.py
just_agents/just_tool.py
just_agents/llm_options.py
just_agents/mcp_client.py
just_agents/patterns/README.md
just_agents/patterns/__init__.py
just_agents/patterns/chain_of_throught.py
just_agents/patterns/interfaces/IThinkingAgent.py
just_agents/patterns/interfaces/ITypedAgent.py
just_agents/protocols/__init__.py
just_agents/protocols/litellm_protocol.py
just_agents/protocols/protocol_factory.py
just_agents/protocols/sse_streaming.py
just_agents/rotate_keys.py
just_agents/types.py
just_agents_core-0.8.7.dist-info/METADATA
just_agents_core-0.8.7.dist-info/WHEEL
just_agents_core-0.8.7.dist-info/RECORD
