Metadata-Version: 2.4
Name: just-agents-core
Version: 0.8.7
Summary: Just Agents - Base Package
License: MIT
Keywords: python,llm,science,review,agents,AI,longevity,biology,coding,web,tools,router
Author: Alex Karmazin
Author-email: karmazinalex@gmail.com
Maintainer: Anton Kulaga
Maintainer-email: antonkulaga@gmail.com
Requires-Python: >=3.10,<3.15
Classifier: Development Status :: 2 - Pre-Alpha
Classifier: Intended Audience :: Developers
Classifier: License :: OSI Approved :: MIT License
Classifier: Operating System :: MacOS :: MacOS X
Classifier: Operating System :: Microsoft :: Windows
Classifier: Operating System :: Unix
Classifier: Programming Language :: Python :: 3
Classifier: Programming Language :: Python :: 3.10
Classifier: Programming Language :: Python :: 3.11
Classifier: Programming Language :: Python :: 3.12
Classifier: Programming Language :: Python :: 3.13
Classifier: Programming Language :: Python :: 3.14
Requires-Dist: docstring_parser (>=0.16)
Requires-Dist: litellm (>=1.72.1)
Requires-Dist: mcp (>=1.9.2)
Requires-Dist: pydantic (>=2.0.0,<3.0.0)
Requires-Dist: python-dotenv (>=1.1.0)
Requires-Dist: rich (>=14.0.0)
Project-URL: Bug Tracker, https://github.com/longevity-genie/just-agents/issues
Project-URL: Documentation, https://just-agents.readthedocs.io/
Project-URL: Homepage, https://github.com/longevity-genie/just-agents
